constants_and_tools/__init__.py
info_tools/__init__.py
os_tools/__init__.py
pandas_tools/__init__.py
polars_tools/__init__.py
singleton_tools/__init__.py
constants_and_tools-2.2.2.dist-info/METADATA
constants_and_tools-2.2.2.dist-info/WHEEL
constants_and_tools-2.2.2.dist-info/top_level.txt
constants_and_tools-2.2.2.dist-info/RECORD
