Metadata-Version: 2.4
Name: constants_and_tools
Version: 2.2.2
Summary: Librería para desarrollo rápido y debug
Home-page: https://github.com/aletheIA-Corp/constants_and_tools
Author: Aletheia_corp
Author-email: dsarabiatorres@gmail.com
Classifier: Programming Language :: Python :: 3
Classifier: License :: OSI Approved :: MIT License
Classifier: Operating System :: OS Independent
Requires-Python: >=3.10
Requires-Dist: colorama>=0.4.6
Requires-Dist: openpyxl>=3.1.5
Requires-Dist: pandas>=2.3.2
Requires-Dist: pyarrow>=21.0.0
Requires-Dist: polars>=1.33.1
Requires-Dist: tabulate>=0.9.0
Dynamic: author
Dynamic: author-email
Dynamic: classifier
Dynamic: description
Dynamic: description-content-type
Dynamic: home-page
Dynamic: requires-dist
Dynamic: requires-python
Dynamic: summary
